README.md
setup.cfg
setup.py
zoofs/__init__.py
zoofs/baseoptimizationalgorithm.py
zoofs/dragonflyoptimization.py
zoofs/geneticoptimization.py
zoofs/gravitationaloptimization.py
zoofs/greywolfoptimization.py
zoofs/harrishawkoptimization.py
zoofs/particleswarmoptimization.py
zoofs.egg-info/PKG-INFO
zoofs.egg-info/SOURCES.txt
zoofs.egg-info/dependency_links.txt
zoofs.egg-info/requires.txt
zoofs.egg-info/top_level.txt
zoofs.egg-info/zip-safe