Metadata-Version: 2.1
Name: zoofs
Version: 0.1.26
Summary: zoofs is a Python library for performing feature selection using an variety of nature inspired wrapper algorithms..
Home-page: https://github.com/jaswinder9051998/zoofs
Author: JaswinderSingh
Author-email: jaswinder9051998@gmail.com
License: Apache License 2.0
Platform: UNKNOWN
Requires-Python: >=3.7
